sphinx_null_theme/__init__.py
sphinx_null_theme/domainindex.html
sphinx_null_theme/genindex.html
sphinx_null_theme/layout.html
sphinx_null_theme/opensearch.xml
sphinx_null_theme/page.html
sphinx_null_theme/py.typed
sphinx_null_theme/search.html
sphinx_null_theme/theme.toml
sphinx_null_theme/toc.py
sphinx_null_theme/locales/.gitkeep
sphinx_null_theme/static/doctools.js
sphinx_null_theme/static/documentation_options.js.jinja
sphinx_null_theme/static/language_data.js.jinja
sphinx_null_theme/static/searchtools.js
sphinx_null_theme/static/sphinx_highlight.js
sphinx_null_theme/static/styles/input.css
sphinx_null_theme-0.1.3.dist-info/entry_points.txt
sphinx_null_theme-0.1.3.dist-info/WHEEL
sphinx_null_theme-0.1.3.dist-info/METADATA
sphinx_null_theme-0.1.3.dist-info/RECORD
