Metadata-Version: 2.4
Name: sphinx_null_theme
Version: 0.1.3
Summary: A weird Sphinx theme with no appereance but functionaly only. Intented to be used as parent theme by other ReadCraft.io themes.
Author: Documatt.com, s.r.o.
Requires-Python: >=3.11
License-Expression: MIT
Classifier: Framework :: Sphinx
Classifier: Framework :: Sphinx :: Theme
Classifier: Development Status :: 5 - Production/Stable
Classifier: Environment :: Web Environment
Classifier: Intended Audience :: Developers
Classifier: Operating System :: OS Independent
Classifier: Topic :: Documentation
Classifier: Topic :: Software Development :: Documentation
Requires-Dist: beautifulsoup4==4.13.3
Requires-Dist: sphinx>=8.0
Project-URL: Home, https://readcraft.io
